LICENSE
MANIFEST.in
README.rst
setup.py
sphinxjp/__init__.py
sphinxjp/tk0miya.py
sphinxjp_tk0miya.egg-info/PKG-INFO
sphinxjp_tk0miya.egg-info/SOURCES.txt
sphinxjp_tk0miya.egg-info/dependency_links.txt
sphinxjp_tk0miya.egg-info/namespace_packages.txt
sphinxjp_tk0miya.egg-info/not-zip-safe
sphinxjp_tk0miya.egg-info/requires.txt
sphinxjp_tk0miya.egg-info/top_level.txt