Metadata-Version: 1.1
Name: sphinxjp-tk0miya
Version: 0.0.1
Summary: Sphinx flicker API extention
Home-page: http://bitbucket.org/r_rudi/sphinxjp-tk0miya
Author: WAKAYAMA Shirou
Author-email: shirou.faw@gmail.com
License: BSD
Download-URL: http://pypi.python.org/pypi/sphinxjp-tk0miya
Platform: any
Classifier: Development Status :: 4 - Beta
Classifier: Environment :: Console
Classifier: Environment :: Web Environment
Classifier: Intended Audience :: Developers
Classifier: License :: OSI Approved :: BSD License
Classifier: Operating System :: OS Independent
Classifier: Programming Language :: Python
Classifier: Topic :: Documentation
Classifier: Topic :: Utilities
